Metadata-Version: 2.1
Name: nimbus-pod
Version: 0.0.5
Summary: Nimbus Pod | FastAPI System Service
Home-page: https://github.com/iyer-cloud/nimbus-pod
Author: Tushar Iyer
Author-email: 
Project-URL: Bug Tracker, https://github.com/iyer-cloud/nimbus-pod/issues
License-File: LICENSE
